app/API.py
app/Config.py
app/Exceptions.py
app/Graph.py
app/Loader/Errors.py
app/Loader/Loader.py
app/Loader/Models.py
app/Loader/__init__.py
app/Types/Doc.py
app/Types/Form.py
app/Types/State.py
app/Types/Transition.py
app/Types/Typedefs.py
app/Types/__init__.py
postoi_resource-0.1.1.dist-info/METADATA
postoi_resource-0.1.1.dist-info/WHEEL
postoi_resource-0.1.1.dist-info/top_level.txt
postoi_resource-0.1.1.dist-info/RECORD
